src/__init__.py
src/content_items.py
pythonlt-0.0.1.dist-info/METADATA
pythonlt-0.0.1.dist-info/WHEEL
pythonlt-0.0.1.dist-info/RECORD
