Metadata-Version: 2.3
Name: pythonlt
Version: 0.0.1
Summary: python.lt static website generator.
Project-URL: homepage, https://github.com/python.lt/python.lt
Author-email: Albertas Gimbutas <albertasgim@gmail.com>
Classifier: Development Status :: 3 - Alpha
Classifier: License :: OSI Approved :: MIT License
Classifier: Natural Language :: English
Classifier: Operating System :: OS Independent
Classifier: Programming Language :: Python
Classifier: Programming Language :: Python :: 3.11
Requires-Python: >=3.11
Provides-Extra: test
Requires-Dist: deadcode; extra == 'test'
Requires-Dist: hatch; extra == 'test'
Requires-Dist: mypy; extra == 'test'
Requires-Dist: pip-audit; extra == 'test'
Requires-Dist: pytest; extra == 'test'
Requires-Dist: pytest-cov; extra == 'test'
Requires-Dist: ruff; extra == 'test'
